.gitignore
build-deploy.sh
import_test.py
pyproject.toml
readme.md
requirements.txt
setup.cfg
setup.py
ezyvetapi/__init__.py
ezyvetapi/configuration_service.py
ezyvetapi/main.py
ezyvetapi.egg-info/PKG-INFO
ezyvetapi.egg-info/SOURCES.txt
ezyvetapi.egg-info/dependency_links.txt
ezyvetapi.egg-info/not-zip-safe
ezyvetapi.egg-info/requires.txt
ezyvetapi.egg-info/top_level.txt
ezyvetapi/models/__init__.py
ezyvetapi/models/animals.py
ezyvetapi/models/appointments.py
ezyvetapi/models/contacts.py
ezyvetapi/models/model.py
ezyvetapi/models/resources.py
ezyvetapi/models/shelter_animal_bookings.py
tests/__init__.py
tests/test_ezy_vet_api.py
tests/models/test_appointments.py
tests/models/test_contacts.py
tests/models/test_resources.py
tests/models/test_shelter_animal_booking.py