Metadata-Version: 2.1
Name: ezyvetapi
Version: 0.0.47
Summary: A package to help facilitate communications with the EzyVet API
Home-page: https://github.com/Cold-Bore-Capital/ezyvet_api_manager
Author: Cold Bore Capital
Author-email: it-group@coldborecapital.com
License: UNKNOWN
Platform: UNKNOWN
Classifier: Programming Language :: Python :: 3.7
Classifier: Topic :: Software Development :: Libraries :: Python Modules
Classifier: Development Status :: 5 - Production/Stable
Requires-Python: >=3.7
